instructprompt/__init__.py
instructprompt-0.1.5.dist-info/LICENSE
instructprompt-0.1.5.dist-info/METADATA
instructprompt-0.1.5.dist-info/WHEEL
instructprompt-0.1.5.dist-info/RECORD
