Metadata-Version: 2.1
Name: instructprompt
Version: 0.1.5
Summary: 
Author: krrishdholakia
Author-email: krrishdholakia@gmail.com
Requires-Python: >=3.8,<4.0
Classifier: Programming Language :: Python :: 3
Classifier: Programming Language :: Python :: 3.8
Classifier: Programming Language :: Python :: 3.9
Classifier: Programming Language :: Python :: 3.10
Classifier: Programming Language :: Python :: 3.11
Requires-Dist: chromadb (>=0.3.25,<0.4.0)
